CHANGELOG.md
MANIFEST.in
README.md
setup.py
google_colab_shell/__init__.py
google_colab_shell.egg-info/PKG-INFO
google_colab_shell.egg-info/SOURCES.txt
google_colab_shell.egg-info/dependency_links.txt
google_colab_shell.egg-info/not-zip-safe
google_colab_shell.egg-info/top_level.txt