Metadata-Version: 2.1
Name: google-colab-shell
Version: 0.2
Summary: An efficent python package to launch terminal in Google Colab
Home-page: https://github.com/singhsidhukuldeep/Google-Colab-Shell
Author: Kuldeep Singh Sidhu
Author-email: singhsidhukuldeep@gmail.com
License: UNKNOWN
Keywords: Google Colab Shell Terminal
Platform: UNKNOWN
Classifier: Development Status :: 5 - Production/Stable
Classifier: Intended Audience :: Education
Classifier: Programming Language :: Python :: 3
Classifier: License :: OSI Approved :: GNU General Public License v3 (GPLv3)
Classifier: Programming Language :: Python
